langchain_anchorbrowser/AnchorBaseTool.py
langchain_anchorbrowser/AnchorContentTool.py
langchain_anchorbrowser/AnchorScreenshotTool.py
langchain_anchorbrowser/AnchorTaskCreateTool.py
langchain_anchorbrowser/AnchorTaskDeleteTool.py
langchain_anchorbrowser/AnchorTaskDeployTool.py
langchain_anchorbrowser/AnchorTaskListExecutionsTool.py
langchain_anchorbrowser/AnchorTaskListTool.py
langchain_anchorbrowser/AnchorTaskRunTool.py
langchain_anchorbrowser/AnchorTaskToolKit.py
langchain_anchorbrowser/AnchorWebTaskTool.py
langchain_anchorbrowser/__init__.py
langchain_anchorbrowser-0.2.0.dist-info/LICENSE
langchain_anchorbrowser-0.2.0.dist-info/METADATA
langchain_anchorbrowser-0.2.0.dist-info/WHEEL
langchain_anchorbrowser-0.2.0.dist-info/RECORD
