Metadata-Version: 2.3
Name: langchain-anchorbrowser
Version: 0.2.0
Summary: Anchor Browser tools for LangChain
License: MIT
Author: Gil Dankner
Author-email: gil@anchorbrowser.io
Requires-Python: >=3.9,<4.0
Classifier: License :: OSI Approved :: MIT License
Classifier: Programming Language :: Python :: 3
Classifier: Programming Language :: Python :: 3.9
Classifier: Programming Language :: Python :: 3.10
Classifier: Programming Language :: Python :: 3.11
Classifier: Programming Language :: Python :: 3.12
Classifier: Programming Language :: Python :: 3.13
Requires-Dist: anchorbrowser (>=0.3.4,<0.4.0)
Requires-Dist: langchain-core (>=0.3.15,<0.4.0)
Requires-Dist: pydantic (>=2.11.1,<3.0.0)
Project-URL: Homepage, https://anchorbrowser.io
Project-URL: Repository, https://github.com/anchorbrowser/langchain-anchorbrowser
